{
  "generator-jhipster": {
    "applicationIndex": 0,
    "applicationType": "monolith",
    "authenticationType": "jwt",
    "baseName": "hr",
    "buildTool": "maven",
    "clientFramework": "angular",
    "creationTimestamp": 1704284328107,
    "devDatabaseType": "postgresql",
    "devServerPort": 4200,
    "entities": ["Employee", "Job", "JobHistory", "Department", "Location", "Country", "Region"],
    "jhipsterVersion": "8.1.0",
    "jwtSecretKey": "ODUxNTNkODkxNDZjNWQ4N2JhYzJhODhmNTViOTQ0NDVmYWQxMzhlYmJiZGFmYmVlZTM1NzE0MjVmNmVkNmI4ZGI3MzMyMTg2MDU2MzJiMGViMjZhYWJjODc5NWVmZTczMmU0ODgyNTc4MGFhYjk0ZDY5N2IyOTY1MTY0OGM5OTQ=",
    "languages": ["en"],
    "lastLiquibaseTimestamp": 1704284327000,
    "nativeLanguage": "en",
    "packageFolder": "org/somesandwich",
    "packageName": "org.somesandwich",
    "prodDatabaseType": "postgresql",
    "searchEngine": "elasticsearch",
    "serverPort": "8080",
    "testFrameworks": ["cypress"]
  }
}
